{
"type": "FeatureCollection",
"name": "geo_42_夜間対応型訪問介護",
"crs": { "type": "name", "properties": { "name": "urn:ogc:def:crs:OGC:1.3:CRS84" } },
"features": [
{ "type": "Feature", "properties": { "内容": "医療法人社団　春秋会　夜間対応型訪問介護ﾍﾙﾊﾟｰｽﾃｰｼｮﾝ・ﾗｲﾌｹｱ【夜間対応型訪問介護】長崎県長崎市大浦町3-21大浦十三番館　2階", "url": "https://www.kaigokensaku.mhlw.go.jp/42/index.php?action_kouhyou_detail_004_kani=true&JigyosyoCd=4290101023-00&ServiceCd=710&Type=search", "url2": "http://www.syunjyu-kai.or.jp/" }, "geometry": { "type": "Point", "coordinates": [ 129.871282611639344, 32.736268400194135 ] } },
{ "type": "Feature", "properties": { "内容": "夜間対応型訪問介護事業所サクラ【夜間対応型訪問介護】佐世保市花園町２０１番地", "url": "https://www.kaigokensaku.mhlw.go.jp/42/index.php?action_kouhyou_detail_004_kani=true&JigyosyoCd=4290200320-00&ServiceCd=710&Type=search", "url2": null }, "geometry": { "type": "Point", "coordinates": [ 129.7224731, 33.1811263 ] } },
{ "type": "Feature", "properties": { "内容": "社会医療法人　玄州会　ホームヘルパーステーションリバティ【夜間対応型訪問介護】長崎県壱岐市郷ノ浦町永田触字八枝275番地2", "url": "https://www.kaigokensaku.mhlw.go.jp/42/index.php?action_kouhyou_detail_004_kani=true&JigyosyoCd=4292100015-00&ServiceCd=710&Type=search", "url2": "http://www.gensyukai.or.jp/" }, "geometry": { "type": "Point", "coordinates": [ 129.697634599999986, 33.7493558 ] } }
]
}
